ethindex/__init__.py
ethindex/cli.py
ethindex/logdecode.py
ethindex/pgimport.py
ethindex/util.py
eth_index-0.4.1.dist-info/LICENSE
eth_index-0.4.1.dist-info/METADATA
eth_index-0.4.1.dist-info/WHEEL
eth_index-0.4.1.dist-info/entry_points.txt
eth_index-0.4.1.dist-info/top_level.txt
eth_index-0.4.1.dist-info/RECORD
