Metadata-Version: 2.1
Name: eth-index
Version: 0.4.1
Summary: Indexer for the ethereum blockchain
Home-page: https://github.com/trustlines-protocol/py-eth-index
Author: Trustlines-Network
Author-email: contact@brainbot.com
License: MIT
Keywords: ethereum indexer database
Platform: UNKNOWN
Classifier: Development Status :: 2 - Pre-Alpha
Classifier: Intended Audience :: Developers
Classifier: License :: OSI Approved :: MIT License
Classifier: Programming Language :: Python :: 3
Classifier: Programming Language :: Python :: 3.6
Requires-Python: >=3.8
Requires-Dist: web3 (>=5.0)
Requires-Dist: psycopg2 (>=2.7)
Requires-Dist: click
Requires-Dist: attrs
Requires-Dist: trustlines-contracts-bin (>=2.0.0)
